LICENSE
MANIFEST.in
pyproject.toml
readsparse_compiler_testing.cpp
setup.py
readsparse/__init__.py
readsparse/cpp_interface.pxi
readsparse/cpp_interface_size_t.pyx
readsparse/cpp_interface_uint64_t.pyx
readsparse.egg-info/PKG-INFO
readsparse.egg-info/SOURCES.txt
readsparse.egg-info/dependency_links.txt
readsparse.egg-info/top_level.txt
src/python_streams.hpp
src/reader.cpp
src/reader.hpp
src/readsparse.hpp
src/readsparse_detemplated.hpp
src/readsparse_internal.hpp
src/utils.hpp
src/writer.cpp
src/writer.hpp